{
  "indexes": [
    {
      "collectionGroup": "Transactions",
      "queryScope": "COLLECTION",
      "fields": [
        {
          "fieldPath": "walletId",
          "order": "ASCENDING"
        },
        {
          "fieldPath": "date",
          "order": "DESCENDING"
        }
      ]
    },
    {
      "collectionGroup": "Wallets",
      "queryScope": "COLLECTION",
      "fields": [
        {
          "fieldPath": "users",
          "arrayConfig": "CONTAINS"
        },
        {
          "fieldPath": "creation_date",
          "order": "DESCENDING"
        }
      ]
    }
  ],
  "fieldOverrides": []
}
